LICENSE
MANIFEST.in
README.md
setup.py
whatsfly/__init__.py
whatsfly/whatsapp.py
whatsfly/whatsmeow.py
whatsfly.egg-info/PKG-INFO
whatsfly.egg-info/SOURCES.txt
whatsfly.egg-info/dependency_links.txt
whatsfly.egg-info/top_level.txt
whatsfly/dependencies/__init__.py
whatsfly/dependencies/whatsmeow/__init__.py
whatsfly/dependencies/whatsmeow/whatsmeow-linux-386.so
whatsfly/dependencies/whatsmeow/whatsmeow-linux-686.so
whatsfly/dependencies/whatsmeow/whatsmeow-linux-amd64.so
whatsfly/dependencies/whatsmeow/whatsmeow-linux-arm64.so
whatsfly/dependencies/whatsmeow/whatsmeow-windows-64.dll