Metadata-Version: 2.1
Name: whatsfly
Version: 0.0.23
Summary: WhatsApp on the fly.
Home-page: https://github.com/cloned-doy/whatsfly
Author: Doy Bachtiar
Author-email: adityabachtiar996@gmail.com
License: MIT
Keywords: whatsfly
Platform: UNKNOWN
Classifier: Intended Audience :: Developers
Classifier: Natural Language :: English
Classifier: Operating System :: Unix
Classifier: Operating System :: MacOS :: MacOS X
Classifier: Operating System :: Microsoft :: Windows
Classifier: Programming Language :: Python
Classifier: Programming Language :: Python :: 3
Classifier: Environment :: Web Environment
Classifier: Topic :: Communications
Classifier: Topic :: Communications :: Chat
Classifier: Topic :: Software Development :: Libraries :: Python Modules
License-File: LICENSE
